README.md
setup.py
SteamedBun_Uninstall.egg-info/PKG-INFO
SteamedBun_Uninstall.egg-info/SOURCES.txt
SteamedBun_Uninstall.egg-info/dependency_links.txt
SteamedBun_Uninstall.egg-info/entry_points.txt
SteamedBun_Uninstall.egg-info/top_level.txt
_CleanPackageTools/CleanDependence.py
_CleanPackageTools/__init__.py