Metadata-Version: 2.1
Name: SteamedBun-Uninstall
Version: 1.0.0
Summary: 虾仁的三方库管理器
Home-page: https://github.com/neihanshenshou/SteamedBunPackageManager
Author: 虾仁
Author-email: neihanshenshou@163.com
License: Apache License 2.0
Platform: MacOS、Window
